smartsheet_helper/__init__.py
smartsheet_helper-0.0.5.dist-info/LICENSE
smartsheet_helper-0.0.5.dist-info/METADATA
smartsheet_helper-0.0.5.dist-info/WHEEL
smartsheet_helper-0.0.5.dist-info/top_level.txt
smartsheet_helper-0.0.5.dist-info/RECORD
