Metadata-Version: 2.2
Name: smartsheet_helper
Version: 0.0.5
Summary: Simple class that helps dealing with smarsheet api
Author-email: shrank <info@murxs.ch>
License: Creative Commons Legal Code
Project-URL: Homepage, https://github.com/shrank/smartsheet-helper
Keywords: smartsheet
Classifier: Programming Language :: Python :: 3
Classifier: Operating System :: OS Independent
Requires-Python: >=3.0
License-File: LICENSE
Requires-Dist: smartsheet-python-sdk
